gcpsecrets/__init__.py
gcpsecrets-0.1.0.dist-info/LICENSE
gcpsecrets-0.1.0.dist-info/WHEEL
gcpsecrets-0.1.0.dist-info/METADATA
gcpsecrets-0.1.0.dist-info/RECORD
